envoy/__init__.py
envoy/__main__.py
envoy/output.py
envoy_env-1.0.1.dist-info/METADATA
envoy_env-1.0.1.dist-info/WHEEL
envoy_env-1.0.1.dist-info/RECORD
