Metadata-Version: 2.4
Name: envoy-env
Version: 1.0.1
Summary: CLI tool to validate that .env files match their linked .env.example files
Requires-Python: >=3.12
Requires-Dist: colorama>=0.4.6
Requires-Dist: typer>=0.15.1
